setup.cfg
setup.py
datetime_utils/__init__.py
datetime_utils/datetime_utils.py
datetime_utils.egg-info/PKG-INFO
datetime_utils.egg-info/SOURCES.txt
datetime_utils.egg-info/dependency_links.txt
datetime_utils.egg-info/requires.txt
datetime_utils.egg-info/top_level.txt