Metadata-Version: 1.1
Name: datetime-utils
Version: 1.0.0
Summary: A DateTime Utils library
Home-page: https://github.com/borbamartin/datetime-utils
Author: Martin Borba
Author-email: borbamartin@gmail.com
License: UNKNOWN
Download-URL: https://github.com/borbamartin/datetime-utils/tarball/1.0.0
Keywords: datetime,utils
Platform: UNKNOWN
